configs/README_TEMPLATE.md
configs/convert_config/run_convert.yaml
configs/convert_config/run_reversed_convert.yaml
configs/deepseek3/predict_deepseek3_671b.yaml
configs/general/llm_finetune_dense_template.yaml
configs/general/llm_finetune_moe_template.yaml
configs/general/llm_pretrain_dense_template.yaml
configs/general/llm_pretrain_moe_template.yaml
configs/general/run_general_task.yaml
configs/glm4/README.md
configs/glm4/finetune_glm4_9b.yaml
configs/glm4/predict_glm4.yaml
configs/glm4/predict_glm4_9b_chat.yaml
configs/glm4/predict_glm4_9b_chat_800I_A2.yaml
configs/glm4_moe/README.md
configs/glm4_moe/predict_glm4_moe.yaml
configs/qwen2/predict_qwen2.yaml
configs/qwen3/README.md
configs/qwen3/finetune_qwen3.yaml
configs/qwen3/predict_qwen3.yaml
configs/qwen3/pretrain_qwen3_32b_4k.yaml
configs/qwen3_moe/README.md
configs/qwen3_moe/predict_qwen3_moe.yaml
configs/qwen3_moe/pretrain_qwen3_30b_a3b_4k.yaml
mindformers/.commit_id
mindformers/VERSION_MAP.json
mindformers/__init__.py
mindformers/mindformer_book.py
mindformers/model_runner.py
mindformers/run_check.py
mindformers/version_control.py
mindformers/checkpoint/__init__.py
mindformers/checkpoint/broadcast.py
mindformers/checkpoint/checkpoint.py
mindformers/checkpoint/fully_parallel.py
mindformers/checkpoint/metadata.py
mindformers/checkpoint/reshard.py
mindformers/checkpoint/sharded_tensor.py
mindformers/checkpoint/utils.py
mindformers/core/__init__.py
mindformers/core/clip_grad.py
mindformers/core/config_args.py
mindformers/core/parallel_config.py
mindformers/core/callback/__init__.py
mindformers/core/callback/build_callback.py
mindformers/core/callback/callback.py
mindformers/core/context/__init__.py
mindformers/core/context/build_context.py
mindformers/core/context/parallel.py
mindformers/core/context/validators.py
mindformers/core/loss/__init__.py
mindformers/core/loss/build_loss.py
mindformers/core/loss/loss.py
mindformers/core/lr/__init__.py
mindformers/core/lr/build_lr.py
mindformers/core/lr/lr_schedule.py
mindformers-1.8.0.dist-info/licenses/LICENSE
mindformers-1.8.0.dist-info/METADATA
mindformers-1.8.0.dist-info/WHEEL
mindformers-1.8.0.dist-info/top_level.txt
mindformers-1.8.0.dist-info/RECORD
