Metadata-Version: 2.4
Name: mindformers
Version: 1.8.0
Summary: mindformers platform: linux, cpu: x86_64
Home-page: https://www.mindspore.cn
Download-URL: https://gitee.com/mindspore/mindformers/tags
Author: The MindSpore Authors
Author-email: contact@mindspore.cn
License: Apache 2.0
Project-URL: Sources, https://gitee.com/mindspore/mindformers
Project-URL: Issue Tracker, https://gitee.com/mindspore/mindformers/issues
Keywords: mindformers
Platform: linux
Classifier: Development Status :: 4 - Beta
Classifier: Environment :: Console
Classifier: Environment :: Web Environment
Classifier: Intended Audience :: Science/Research
Classifier: Intended Audience :: Developers
Classifier: License :: OSI Approved :: Apache Software License
Classifier: Programming Language :: Python :: 3 :: Only
Classifier: Programming Language :: Python :: 3.7
Classifier: Programming Language :: Python :: 3.8
Classifier: Programming Language :: Python :: 3.9
Classifier: Programming Language :: Python :: 3.10
Classifier: Programming Language :: Python :: 3.11
Classifier: Topic :: Scientific/Engineering
Classifier: Topic :: Scientific/Engineering :: Artificial Intelligence
Classifier: Topic :: Software Development
Classifier: Topic :: Software Development :: Libraries
Classifier: Topic :: Software Development :: Libraries :: Python Modules
Requires-Python: >=3.7
License-File: LICENSE
Requires-Dist: setuptools
Requires-Dist: sentencepiece>=0.2.0
Requires-Dist: ftfy>=6.1.1
Requires-Dist: regex>=2022.10.31
Requires-Dist: tqdm>=4.65.0
Requires-Dist: pyyaml>=6.0
Requires-Dist: jieba>=0.42.1
Requires-Dist: rouge_chinese>=1.0.3
Requires-Dist: nltk==3.9.1
Requires-Dist: mindpet==1.0.4
Requires-Dist: opencv-python-headless
Requires-Dist: pyarrow==19.0.0
Requires-Dist: tokenizers
Requires-Dist: astunparse>=1.6.3
Requires-Dist: numpy<2.0.0
Requires-Dist: tiktoken
Requires-Dist: jinja2
Requires-Dist: setproctitle
Requires-Dist: safetensors
Requires-Dist: tensorboardX
Requires-Dist: deprecated>=1.2.0
Requires-Dist: pybind11
Requires-Dist: transformers==4.57.1
Requires-Dist: datasets>=4.0.0
Requires-Dist: mindspore~=2.7.2
Dynamic: author
Dynamic: author-email
Dynamic: classifier
Dynamic: description
Dynamic: description-content-type
Dynamic: download-url
Dynamic: home-page
Dynamic: keywords
Dynamic: license
Dynamic: license-file
Dynamic: platform
Dynamic: project-url
Dynamic: requires-dist
Dynamic: requires-python
Dynamic: summary
